mibiscreen/__init__.py
mibiscreen/analysis/__init__.py
mibiscreen/analysis/reduction/__init__.py
mibiscreen/analysis/reduction/ordination.py
mibiscreen/analysis/reduction/stable_isotope_regression.py
mibiscreen/analysis/reduction/transformation.py
mibiscreen/analysis/sample/__init__.py
mibiscreen/analysis/sample/concentrations.py
mibiscreen/analysis/sample/intervention.py
mibiscreen/analysis/sample/properties.py
mibiscreen/analysis/sample/screening_NA.py
mibiscreen/data/__init__.py
mibiscreen/data/check_data.py
mibiscreen/data/load_data.py
mibiscreen/data/set_data.py
mibiscreen/data/example_data/__init__.py
mibiscreen/data/example_data/example_data.csv
mibiscreen/data/example_data/example_data.py
mibiscreen/data/example_data/example_data.xlsx
mibiscreen/data/settings/__init__.py
mibiscreen/data/settings/contaminants.py
mibiscreen/data/settings/environment.py
mibiscreen/data/settings/isotopes.py
mibiscreen/data/settings/metabolites.py
mibiscreen/data/settings/sample_settings.py
mibiscreen/data/settings/standard_names.py
mibiscreen/data/settings/unit_settings.py
mibiscreen/visualize/__init__.py
mibiscreen/visualize/ordination_plots.py
mibiscreen/visualize/screening_plots.py
mibiscreen/visualize/stable_isotope_plots.py
mibiscreen-0.6.0.dist-info/licenses/LICENSE
mibiscreen-0.6.0.dist-info/METADATA
mibiscreen-0.6.0.dist-info/WHEEL
mibiscreen-0.6.0.dist-info/top_level.txt
mibiscreen-0.6.0.dist-info/RECORD
