Metadata-Version: 2.4
Name: mibiscreen
Version: 0.6.0
Summary: A collection of analytical and semi-semianalytical solutions for hydrogeological transport phenomena
Author-email: Alraune Zech <a.zech@uu.nl>
License:                                  Apache License
Project-URL: Repository, https://github.com/MiBiPreT/mibiscreen
Project-URL: Issues, https://github.com/MiBiPreT/mibiscreen/issues
Project-URL: Changelog, https://github.com/MiBiPreT/mibiscreen/CHANGELOG.md
Keywords: groundwater,contaminant transport
Classifier: Development Status :: 2 - Pre-Alpha
Classifier: Intended Audience :: Developers
Classifier: Intended Audience :: Science/Research
Classifier: License :: OSI Approved :: Apache Software License
Classifier: Natural Language :: English
Classifier: Programming Language :: Python :: 3
Classifier: Programming Language :: Python :: 3.8
Classifier: Programming Language :: Python :: 3.9
Classifier: Programming Language :: Python :: 3.10
Classifier: Programming Language :: Python :: 3.11
Classifier: Programming Language :: Python :: 3.12
Requires-Python: >=3.8
License-File: LICENSE
Requires-Dist: pandas
Requires-Dist: openpyxl
Requires-Dist: matplotlib
Requires-Dist: IPython
Requires-Dist: adjustText
Requires-Dist: scikit-learn
Requires-Dist: scikit-bio
Provides-Extra: dev
Requires-Dist: build; extra == "dev"
Requires-Dist: bump-my-version; extra == "dev"
Requires-Dist: coverage[toml]; extra == "dev"
Requires-Dist: pytest; extra == "dev"
Requires-Dist: pytest-cov; extra == "dev"
Requires-Dist: ruff; extra == "dev"
Requires-Dist: tox; extra == "dev"
Requires-Dist: nb-clean==4.0.1; extra == "dev"
Provides-Extra: publishing
Requires-Dist: build; extra == "publishing"
Requires-Dist: twine; extra == "publishing"
Requires-Dist: wheel; extra == "publishing"
Provides-Extra: doc
Requires-Dist: mkdocs>=1.4.2; extra == "doc"
Requires-Dist: mkdocs-material>=8.2.7; extra == "doc"
Requires-Dist: mkdocstrings[python]==0.27.0; extra == "doc"
Requires-Dist: mdx-include>=1.4.1; extra == "doc"
Requires-Dist: mkdocs-markdownextradata-plugin>=0.2.5; extra == "doc"
Dynamic: license-file
